LICENSE
MANIFEST.in
README.rst
setup.py
DjangoPackage_v0.0.6.egg-info/PKG-INFO
DjangoPackage_v0.0.6.egg-info/SOURCES.txt
DjangoPackage_v0.0.6.egg-info/dependency_links.txt
DjangoPackage_v0.0.6.egg-info/requires.txt
DjangoPackage_v0.0.6.egg-info/top_level.txt
blog/__init__.py
blog/admin.py
blog/apps.py
blog/forms.py
blog/models.py
blog/tests.py
blog/urls.py
blog/views.py
blog/migrations/0001_initial.py
blog/migrations/__init__.py
blog/templates/blog_category.html
blog/templates/blog_detail.html
blog/templates/blog_index.html
personal_portfolio/__init__.py
personal_portfolio/settings.py
personal_portfolio/urls.py
personal_portfolio/wsgi.py
personal_portfolio/templates/base.html
projects/__init__.py
projects/admin.py
projects/apps.py
projects/models.py
projects/tests.py
projects/urls.py
projects/views.py
projects/migrations/0001_initial.py
projects/migrations/__init__.py
projects/static/img/project1.png
projects/static/img/project2.png
projects/static/img/project3.png
projects/templates/project_detail.html
projects/templates/project_index.html